{"org.jkiss.dbeaver.ext.postgresql.model.PostgreView":{"pageId":"default.object.editor","folderId":"Columns"},"org.jkiss.dbeaver.ext.postgresql.model.PostgreDatabase":{"pageId":"default.object.editor","folderId":"Schemas"},"org.jkiss.dbeaver.registry.DataSourceDescriptor":{"pageId":"default.object.editor"},"org.jkiss.dbeaver.ext.postgresql.model.PostgreTableRegular":{"pageId":"default.object.editor","folderId":"Columns"},"org.jkiss.dbeaver.ext.postgresql.model.PostgreMaterializedView":{"pageId":"default.object.editor","folderId":"postgresql.source.view"},"org.jkiss.dbeaver.ext.postgresql.model.PostgreSchema":{"pageId":"default.object.editor","folderId":"Tables"},"org.jkiss.dbeaver.ext.postgresql.model.PostgreRole":{"pageId":"default.object.editor","folderId":"postgresql.source.view"},"org.jkiss.dbeaver.ext.postgresql.model.PostgreTrigger":{"pageId":"default.object.editor"},"org.jkiss.dbeaver.ext.postgresql.model.PostgreIndex":{"pageId":"default.object.editor","folderId":"Index columns"},"org.jkiss.dbeaver.ext.postgresql.model.PostgreTableColumn":{"pageId":"default.object.editor","folderId":"postgresql.table.permissions"}}